diblogeo/__init__.py
diblogeo/util.py
diblogeo-0.1.0rc3.dist-info/DESCRIPTION.rst
diblogeo-0.1.0rc3.dist-info/METADATA
diblogeo-0.1.0rc3.dist-info/RECORD
diblogeo-0.1.0rc3.dist-info/WHEEL
diblogeo-0.1.0rc3.dist-info/metadata.json
diblogeo-0.1.0rc3.dist-info/top_level.txt
