Metadata-Version: 2.0
Name: diblogeo
Version: 0.1.0rc3
Summary: Python Geolocation API
Home-page: https://pypi.python.org/pypi/diblogeo
Author: Henrik Ankersoe
Author-email: henrik@diblo.dk
License: GPL v3
Keywords: geocode geocoding geographical maps earth distance bearing
Platform: UNKNOWN
Classifier: Development Status :: 4 - Beta
Classifier: Intended Audience :: Developers
Classifier: Programming Language :: Python
Classifier: Topic :: Software Development :: Build Tools
Classifier: Topic :: Software Development :: Libraries :: Python Modules
Classifier: License :: OSI Approved :: GNU General Public License v3 (GPLv3)
Classifier: Programming Language :: Python :: 2.7
